keyboardpaster/__init__.py
keyboardpaster/app.py
keyboardpaster/keyboard_layout_detector.py
keyboardpaster/keyboardpaster_app.kv
keyboardpaster/shared_resources.py
keyboardpaster/modules/__init__.py
keyboardpaster/modules/autoupdate.py
keyboardpaster-0.1.24.dist-info/licenses/LICENSE
keyboardpaster-0.1.24.dist-info/METADATA
keyboardpaster-0.1.24.dist-info/WHEEL
keyboardpaster-0.1.24.dist-info/entry_points.txt
keyboardpaster-0.1.24.dist-info/top_level.txt
keyboardpaster-0.1.24.dist-info/RECORD
