Metadata-Version: 2.4
Name: KeyboardPaster
Version: 0.1.24
Summary: A Python package to type text using the keyboard module
Home-page: https://github.com/KnutssonDevelopment/KeyboardPaster
Author: Brian Knutsson
Author-email: development@knutsson.it
Classifier: Development Status :: 3 - Alpha
Classifier: Intended Audience :: End Users/Desktop
Classifier: License :: OSI Approved :: MIT License
Classifier: Operating System :: Microsoft :: Windows
Classifier: Operating System :: POSIX :: Linux
Classifier: Operating System :: MacOS :: MacOS X
Classifier: Programming Language :: Python :: 3
Classifier: Programming Language :: Python :: 3.10
Classifier: Programming Language :: Python :: 3.12
Classifier: Programming Language :: Python :: 3.13
Requires-Python: >=3.10
License-File: LICENSE
Requires-Dist: pynput
Requires-Dist: kivy
Requires-Dist: kivymd
Requires-Dist: requests
Provides-Extra: windows
Requires-Dist: pywin32; extra == "windows"
Provides-Extra: linux
Requires-Dist: setuptools; extra == "linux"
Provides-Extra: macos
Requires-Dist: setuptools; extra == "macos"
Dynamic: author
Dynamic: author-email
Dynamic: classifier
Dynamic: description
Dynamic: description-content-type
Dynamic: home-page
Dynamic: license-file
Dynamic: provides-extra
Dynamic: requires-dist
Dynamic: requires-python
Dynamic: summary
